toy18_uvvis.py
toy18_uvvis-0.1.1603889316.dist-info/METADATA
toy18_uvvis-0.1.1603889316.dist-info/WHEEL
toy18_uvvis-0.1.1603889316.dist-info/top_level.txt
toy18_uvvis-0.1.1603889316.dist-info/RECORD
