Metadata-Version: 2.1
Name: toy18-uvvis
Version: 0.1.1603889316
Summary: Toy18 UVVis Detector
Home-page: https://github.com/JulianKimmig/toy18_uvvis
Author: Julian Kimmig
Author-email: julian-kimmig@gmx.net
License: UNKNOWN
Platform: UNKNOWN
Classifier: Programming Language :: Python :: 3
Classifier: License :: OSI Approved :: MIT License
Classifier: Operating System :: OS Independent
Requires-Dist: numpy
Requires-Dist: pandas
Requires-Dist: matplotlib
Requires-Dist: data-recorder
Requires-Dist: hardware-communicator
